kontor/__init__.py
kontor/applicant.py
kontor/bureau.py
kontor/clerk.py
kontor/defines.py
kontor/exceptions.py
kontor/functions.py
kontor/py.typed
kontor/structures.py
kontor-1.0.0.dist-info/licenses/LICENSE
kontor-1.0.0.dist-info/METADATA
kontor-1.0.0.dist-info/WHEEL
kontor-1.0.0.dist-info/top_level.txt
kontor-1.0.0.dist-info/zip-safe
kontor-1.0.0.dist-info/RECORD
