Metadata-Version: 2.4
Name: kontor
Version: 1.0.0
Summary: kontor package
Home-page: https://github.com/morwy/kontor
Author: Pavel Ivanov
Author-email: 
License: BSD-3-Clause
Project-URL: Bug Tracker, https://github.com/morwy/kontor/issues
Project-URL: Source Code, https://github.com/morwy/kontor
Keywords: client,server,transfer
Platform: any
Classifier: Development Status :: 2 - Pre-Alpha
Classifier: Environment :: Console
Classifier: Intended Audience :: Developers
Classifier: License :: OSI Approved :: BSD License
Classifier: Operating System :: OS Independent
Classifier: Programming Language :: Python
Classifier: Topic :: Software Development :: Libraries :: Python Modules
Classifier: Programming Language :: Python :: 3.7
Classifier: Programming Language :: Python :: 3.8
Classifier: Programming Language :: Python :: 3.9
Classifier: Programming Language :: Python :: 3.10
Classifier: Programming Language :: Python :: 3.11
Classifier: Programming Language :: Python :: 3.12
Classifier: Programming Language :: Python :: 3.13
Requires-Python: >=3.7
License-File: LICENSE
Requires-Dist: dacite
Provides-Extra: test
Requires-Dist: pytest; extra == "test"
Dynamic: license-file
